{
  "id": "scenario_microsoft_2014_2016",
  "status": "active",
  "company": {
    "name": "Microsoft",
    "ticker": "MSFT",
    "exchange": "NASDAQ",
    "sector": "Information Technology",
    "industry": "Systems Software",
    "country": "United States",
    "acceptedNames": ["microsoft", "msft"],
    "identityBannedTerms": ["Satya Nadella", "Windows", "Azure", "Office 365", "Xbox"]
  },
  "scenario": {
    "title": "Footprint Bet",
    "decisionDate": "2014-01-02",
    "endDate": "2016-01-04",
    "decisionDateLabel": "Jan 2014",
    "outcomeLabel": "Jan 2014 → Jan 2016",
    "holdingPeriodLabel": "2 years",
    "era": "Cloud software expansion",
    "eraId": "cloud_software_expansion",
    "contentPackIds": ["mvp_core", "sample_seed"],
    "difficultySupported": ["easy", "medium", "hard"]
  },
  "marketData": {
    "startingPrice": 37,
    "endingPrice": 51,
    "actualReturnPercent": 0.38,
    "usesSplitAdjustedPrices": true,
    "usesTotalReturn": false,
    "preDecisionChartStartDate": "2011-01-03",
    "preDecisionChartEndDate": "2014-01-02",
    "outcomeChartStartDate": "2014-01-02",
    "outcomeChartEndDate": "2016-01-04",
    "lookbackPrices": [26, 25, 27, 28, 30, 32, 34, 37],
    "outcomePrices": [37, 40, 44, 47, 43, 46, 49, 51]
  },
  "hiddenCard": {
    "easy": {
      "companyDescription": "A mature enterprise software company shifting more of its business toward cloud subscriptions.",
      "macroContext": "Businesses are moving more computing work from owned infrastructure to rented cloud services.",
      "situation": "Can a large installed base revive growth through subscriptions before faster rivals define the market?",
      "longCase": "Long-standing corporate relationships could accelerate adoption of cloud and subscription offerings.",
      "shortCase": "Mature product lines may shrink before replacements contribute enough growth to satisfy investors.",
      "setupHints": [
        "Years of investor frustration raise the bar for whether this pivot looks credible."
      ]
    },
    "medium": {
      "companyDescription": "A diversified technology vendor selling mainly to businesses.",
      "macroContext": "Corporate buyers are changing how they purchase and consume software and infrastructure.",
      "situation": "Can the firm refresh growth before mature offerings slow too far?",
      "longCase": "Deep customer relationships could help introduce newer offerings at lower acquisition cost.",
      "shortCase": "Legacy dependence and faster-moving rivals can keep growth muted longer than investors tolerate.",
      "setupHints": []
    },
    "hard": {
      "companyDescription": "An enterprise technology company.",
      "macroContext": "Business technology spending is being reallocated across old and new delivery models.",
      "situation": "Will an established vendor convert its footprint into renewed growth in time?",
      "longCase": "An existing commercial footprint can lower the cost of distributing newer products.",
      "shortCase": "If replacements ramp slowly, mature-line pressure can dominate the equity story.",
      "setupHints": []
    }
  },
  "reveal": {
    "shortText": "That was Microsoft. The cloud pivot under Satya Nadella started changing how investors valued the old software giant.",
    "funFact": "By early 2016, the market had started rewarding the company for cloud growth and recurring software revenue.",
    "whyItMoved": [
      "Cloud and subscription revenue became more visible.",
      "Investors began re-rating recurring software streams.",
      "Enterprise relationships helped distribution of newer offerings."
    ]
  },
  "sources": [
    {
      "label": "Prototype sample seed",
      "url": "https://example.com/sources/microsoft-2014-2016",
      "notes": "Placeholder sample content for Phase 3 pipeline; not production research."
    }
  ],
  "review": {
    "generatedByAi": true,
    "humanReviewed": false,
    "reviewNotes": "Medium/Hard rewritten after H023 Gate 2 identity failures (multi-line vendor + commercial relationships → subscription triangulation). Intended peer set: Microsoft / Oracle / IBM / SAP / Cisco-class enterprise vendors. Easy unchanged; Medium/Hard Gate 2 pending re-judge.",
    "factBank": {
      "revealOnly": ["Microsoft brand", "Satya Nadella", "Azure", "cloud subscription pivot narrative"],
      "decisionUseful": ["business-customer footprint", "mature-line drag", "newer-product distribution leverage", "changing corporate buying models"],
      "prohibited": ["Windows", "Azure", "Office 365", "Satya Nadella", "subscription-from-installed-base wording", "hosted-services-only framing"]
    },
    "easyLikelyGuesses": ["Microsoft", "IBM", "Oracle"],
    "mediumLikelyGuesses": ["Microsoft", "Oracle", "IBM", "SAP"],
    "hardLikelyGuesses": ["Microsoft", "Oracle", "IBM", "SAP", "Cisco", "HP"],
    "gate2": {
      "easy": {
        "payloadHash": "sha256:055472a1d7aa356b3719fe8ed8ac7c27e7d89bd2f9a2d5aac7366880b73328e6",
        "model": "grok-4.5",
        "promptVersion": "guess.v1+direction.v1",
        "testedAt": "2026-07-09T18:30:00.000Z",
        "guesses": [
          {
            "company": "Microsoft",
            "confidence": 88,
            "pointingFact": "Jan 2014 mature enterprise software giant shifting to cloud subscriptions after years of investor frustration"
          },
          {
            "company": "Oracle",
            "confidence": 48,
            "pointingFact": "Large enterprise software vendor converting licenses to cloud/subscription"
          },
          {
            "company": "IBM",
            "confidence": 40,
            "pointingFact": "Mature enterprise tech firm trying to revive growth as IT moves to rented cloud services"
          },
          {
            "company": "SAP",
            "confidence": 30,
            "pointingFact": "Enterprise software installed-base story pivoting toward subscription offerings"
          },
          {
            "company": "Adobe",
            "confidence": 22,
            "pointingFact": "Software company known for subscription transition from mature product lines"
          }
        ],
        "direction": {
          "call": "long",
          "confidence": 62,
          "cue": "Broad corporate installed base can accelerate cloud subscription adoption if the pivot is credible"
        }
      }
    }
  }
}
